gsw-3.6.20.dist-info/RECORD
gsw-3.6.20.dist-info/WHEEL
gsw-3.6.20.dist-info/top_level.txt
gsw-3.6.20.dist-info/METADATA
gsw-3.6.20.dist-info/licenses/LICENSE.txt
gsw/_gsw_ufuncs.cpython-311-darwin.so
gsw/stability.py
gsw/interpolation.py
gsw/_version.py
gsw/conversions.py
gsw/utility.py
gsw/__init__.py
gsw/energy.py
gsw/_utilities.py
gsw/_fixed_wrapped_ufuncs.py
gsw/density.py
gsw/ice.py
gsw/_wrapped_ufuncs.py
gsw/geostrophy.py
gsw/freezing.py
gsw/tests/test_interpolation.py
gsw/tests/geo_strf_velocity.npy
gsw/tests/gsw_check_functions_save.m
gsw/tests/test_geostrophy.py
gsw/tests/_WIP_test_ufuncs.py
gsw/tests/check_functions.py
gsw/tests/test_xarray.py
gsw/tests/geo_strf_dyn_height.npy
gsw/tests/test_utility.py
gsw/tests/test_check_functions.py
gsw/tests/gsw_cv_v3_0.npz
gsw/tests/test_dll_export.py
gsw/tests/write_geo_npyfiles.py
gsw/tests/list_check_functions.py
gsw/tests/test_gibbs.py
