Metadata-Version: 2.4
Name: gsw
Version: 3.6.20
Summary: Gibbs Seawater Oceanographic Package of TEOS-10
Author-email: "Eric Firing, Filipe Fernandes" <efiring@hawaii.edu>
License: BSD-3-Clause
Project-URL: documentation, https://teos-10.github.io/GSW-Python/
Project-URL: homepage, https://www.teos-10.org/
Project-URL: repository, https://github.com/TEOS-10/GSW-python
Classifier: Development Status :: 5 - Production/Stable
Classifier: Intended Audience :: Science/Research
Classifier: License :: OSI Approved :: BSD License
Classifier: Operating System :: OS Independent
Classifier: Programming Language :: Python
Classifier: Programming Language :: Python :: 3 :: Only
Classifier: Programming Language :: Python :: 3.8
Classifier: Programming Language :: Python :: 3.9
Classifier: Programming Language :: Python :: 3.10
Classifier: Programming Language :: Python :: 3.11
Classifier: Programming Language :: Python :: 3.12
Classifier: Programming Language :: Python :: 3.13
Classifier: Topic :: Scientific/Engineering
Requires-Python: >=3.8
License-File: LICENSE.txt
Requires-Dist: numpy>=1.21
Dynamic: license-file
